CHANGES.txt
LICENSE.txt
MANIFEST.in
README.txt
buildout.cfg
setup.py
src/j01/__init__.py
src/j01.datepickerzebra.egg-info/PKG-INFO
src/j01.datepickerzebra.egg-info/SOURCES.txt
src/j01.datepickerzebra.egg-info/dependency_links.txt
src/j01.datepickerzebra.egg-info/namespace_packages.txt
src/j01.datepickerzebra.egg-info/not-zip-safe
src/j01.datepickerzebra.egg-info/requires.txt
src/j01.datepickerzebra.egg-info/top_level.txt
src/j01/datepickerzebra/README.txt
src/j01/datepickerzebra/__init__.py
src/j01/datepickerzebra/browser.zcml
src/j01/datepickerzebra/configure.zcml
src/j01/datepickerzebra/converter.py
src/j01/datepickerzebra/input.pt
src/j01/datepickerzebra/interfaces.py
src/j01/datepickerzebra/tests.py
src/j01/datepickerzebra/widget.py
src/j01/datepickerzebra/css/j01.datepicker.zebra.css
src/j01/datepickerzebra/img/zebraDatePickerIcon.png
src/j01/datepickerzebra/js/j01.datepicker.zebra.js
src/j01/datepickerzebra/js/j01.datepicker.zebra.min.js
src/j01/datepickerzebra/less/j01.datepicker.zebra.less
src/j01/datepickerzebra/less/source/core.less
src/j01/datepickerzebra/less/source/variables.less