Metadata-Version: 2.1
Name: j01.datepickerzebra
Version: 4.0.0
Summary: JQuery zebra datepicker based on 3c.form for Zope 3
Home-page: http://pypi.org/pypi/j01.datepickerzebra
Author: Roger Ineichen, Projekt01 GmbH
Author-email: dev@projekt01.ch
License: LGPLv3
Keywords: J01 JQuery zebra datepicker date z3c form widget Zope3
Platform: UNKNOWN
Classifier: Development Status :: 5 - Production/Stable
Classifier: Environment :: Web Environment
Classifier: Intended Audience :: Developers
Classifier: License :: OSI Approved :: GNU Lesser General Public License v3 (LGPLv3)
Classifier: Programming Language :: Python
Classifier: Natural Language :: English
Classifier: Operating System :: OS Independent
Classifier: Topic :: Internet :: WWW/HTTP
Classifier: Framework :: Zope3
Provides-Extra: test
